[
    {
        "key": "jVQn-ykoq-f2jB",
        "edge": "PLUS_EV_AVERAGE",
        "lastFoundAt": "2024-10-14T16:43:00.900Z",
        "type": "MONEYLINE",
        "market_name": "Crvena zvezda @ Fenerbah\u00e7e",
        "participants": [
            "Crvena zvezda",
            "Fenerbah\u00e7e"
        ],
        "outcome_payout": 3.9,
        "source": "BOVADA",
        "participant": "Crvena zvezda",
        "sport": "BASKETBALL",
        "implied_probability": 25.958943,
        "profit_potential": 290.0,
        "EV": 1.2398777,
        "event_start_time": "2024-10-15T17:45:00.000Z",
        "competition_instance_name": "2024-25 EuroLeague"
    },
    {
        "key": "0Lh0-ykoq-pUNk",
        "edge": "PLUS_EV_AVERAGE",
        "lastFoundAt": "2024-10-14T16:43:00.900Z",
        "type": "MONEYLINE",
        "market_name": "Las Vegas Raiders @ Los Angeles Rams",
        "participants": [
            "Los Angeles Rams",
            "Las Vegas Raiders"
        ],
        "outcome_payout": 3.1,
        "source": "BOVADA",
        "participant": "Las Vegas Raiders",
        "sport": "AMERICAN_FOOTBALL",
        "implied_probability": 32.4589,
        "profit_potential": 210.0,
        "EV": 0.62259,
        "event_start_time": "2024-10-20T20:05:00.000Z",
        "competition_instance_name": "2024-25 National Football League"
    },
    {
        "key": "d3Ps-ykoq-oMHt",
        "edge": "PLUS_EV_AVERAGE",
        "lastFoundAt": "2024-10-14T16:43:00.900Z",
        "type": "MONEYLINE",
        "market_name": "Buffalo Bills @ New York Jets",
        "participants": [
            "Buffalo Bills",
            "New York Jets"
        ],
        "outcome_payout": 2.1,
        "source": "BOVADA",
        "participant": "New York Jets",
        "sport": "AMERICAN_FOOTBALL",
        "implied_probability": 47.727194,
        "profit_potential": 110.0,
        "EV": 0.2271074,
        "event_start_time": "2024-10-15T00:15:00.000Z",
        "competition_instance_name": "2024-25 National Football League"
    },
    {
        "key": "GMK0-ykoq-TdUD",
        "edge": "PLUS_EV_AVERAGE",
        "lastFoundAt": "2024-10-14T16:43:00.900Z",
        "type": "MONEYLINE",
        "market_name": "Las Vegas Raiders @ Los Angeles Rams",
        "participants": [
            "Los Angeles Rams",
            "Las Vegas Raiders"
        ],
        "outcome_payout": 3.1,
        "source": "FAN_DUEL",
        "participant": "Las Vegas Raiders",
        "sport": "AMERICAN_FOOTBALL",
        "implied_probability": 32.4589,
        "profit_potential": 210.0,
        "EV": 0.62259,
        "event_start_time": "2024-10-20T20:05:00.000Z",
        "competition_instance_name": "2024-25 National Football League"
    },
    {
        "key": "A8LP-ykoq-2lK3",
        "edge": "PLUS_EV_AVERAGE",
        "lastFoundAt": "2024-10-14T16:43:00.900Z",
        "type": "MONEYLINE_3WAY",
        "market_name": "Napoli @ Empoli",
        "participants": [
            "Napoli",
            "Empoli"
        ],
        "outcome_payout": 5.7,
        "source": "FAN_DUEL",
        "participant": "Empoli",
        "sport": "SOCCER",
        "implied_probability": 17.857032,
        "profit_potential": 470.0,
        "EV": 1.7850824,
        "event_start_time": "2024-10-20T10:30:00.000Z",
        "competition_instance_name": "2024-25 Italian Serie A"
    },
    {
        "key": "0OuU-ykoq-gJ9k",
        "edge": "PLUS_EV_AVERAGE",
        "lastFoundAt": "2024-10-14T16:43:00.900Z",
        "type": "MONEYLINE_3WAY",
        "market_name": "Hellas Verona @ Atalanta",
        "participants": [
            "Hellas Verona",
            "Atalanta"
        ],
        "outcome_payout": 5.2,
        "source": "BOVADA",
        "participant": null,
        "sport": null,
        "implied_probability": 19.441214,
        "profit_potential": 420.0,
        "EV": 1.0943128,
        "event_start_time": "2024-10-26T18:45:00.000Z",
        "competition_instance_name": "2024-25 Italian Serie A"
    },
    {
        "key": "0Yak-ykoq-r6Ft",
        "edge": "PLUS_EV_AVERAGE",
        "lastFoundAt": "2024-10-14T16:43:00.900Z",
        "type": "MONEYLINE_3WAY",
        "market_name": "Udinese @ AC Milan",
        "participants": [
            "AC Milan",
            "Udinese"
        ],
        "outcome_payout": 8.5,
        "source": "BET_RIVERS",
        "participant": "Udinese",
        "sport": "SOCCER",
        "implied_probability": 12.072465,
        "profit_potential": 750.0,
        "EV": 2.6159525,
        "event_start_time": "2024-10-19T16:00:00.000Z",
        "competition_instance_name": "2024-25 Italian Serie A"
    },
    {
        "key": "7rsV-ykoq-Nf9U",
        "edge": "PLUS_EV_AVERAGE",
        "lastFoundAt": "2024-10-14T16:43:00.900Z",
        "type": "MONEYLINE_3WAY",
        "market_name": "Atalanta @ Venezia",
        "participants": [
            "Atalanta",
            "Venezia"
        ],
        "outcome_payout": 4.4,
        "source": "BET_RIVERS",
        "participant": null,
        "sport": null,
        "implied_probability": 23.152726,
        "profit_potential": 340.0,
        "EV": 1.8719944,
        "event_start_time": "2024-10-20T13:00:00.000Z",
        "competition_instance_name": "2024-25 Italian Serie A"
    },
    {
        "key": "agKf-ykoq-pXlJ",
        "edge": "PLUS_EV_AVERAGE",
        "lastFoundAt": "2024-10-14T16:43:00.900Z",
        "type": "MONEYLINE_3WAY",
        "market_name": "Inter Milan @ AS Roma",
        "participants": [
            "Inter Milan",
            "AS Roma"
        ],
        "outcome_payout": 4.0,
        "source": "BET_RIVERS",
        "participant": null,
        "sport": null,
        "implied_probability": 25.029008,
        "profit_potential": 300.0,
        "EV": 0.116032,
        "event_start_time": "2024-10-20T18:45:00.000Z",
        "competition_instance_name": "2024-25 Italian Serie A"
    },
    {
        "key": "eAg4-ykoq-2ivM",
        "edge": "PLUS_EV_AVERAGE",
        "lastFoundAt": "2024-10-14T16:43:00.900Z",
        "type": "MONEYLINE_3WAY",
        "market_name": "Hellas Verona @ Atalanta",
        "participants": [
            "Hellas Verona",
            "Atalanta"
        ],
        "outcome_payout": 8.5,
        "source": "BET_RIVERS",
        "participant": "Hellas Verona",
        "sport": "SOCCER",
        "implied_probability": 12.776968,
        "profit_potential": 750.0,
        "EV": 8.604228,
        "event_start_time": "2024-10-26T18:45:00.000Z",
        "competition_instance_name": "2024-25 Italian Serie A"
    },
    {
        "key": "I0Pv-ykoq-dB2i",
        "edge": "PLUS_EV_AVERAGE",
        "lastFoundAt": "2024-10-14T16:43:00.900Z",
        "type": "MONEYLINE_3WAY",
        "market_name": "Udinese @ AC Milan",
        "participants": [
            "AC Milan",
            "Udinese"
        ],
        "outcome_payout": 5.4,
        "source": "BET_RIVERS",
        "participant": null,
        "sport": null,
        "implied_probability": 18.604433,
        "profit_potential": 440.0,
        "EV": 0.4639382,
        "event_start_time": "2024-10-19T16:00:00.000Z",
        "competition_instance_name": "2024-25 Italian Serie A"
    },
    {
        "key": "Pg3r-ykoq-UEPH",
        "edge": "PLUS_EV_AVERAGE",
        "lastFoundAt": "2024-10-14T16:43:00.900Z",
        "type": "MONEYLINE_3WAY",
        "market_name": "Inter Milan @ AS Roma",
        "participants": [
            "Inter Milan",
            "AS Roma"
        ],
        "outcome_payout": 4.2,
        "source": "BET_RIVERS",
        "participant": "AS Roma",
        "sport": "SOCCER",
        "implied_probability": 23.864465,
        "profit_potential": 320.0,
        "EV": 0.230753,
        "event_start_time": "2024-10-20T18:45:00.000Z",
        "competition_instance_name": "2024-25 Italian Serie A"
    },
    {
        "key": "qQ70-ykoq-2OBQ",
        "edge": "PLUS_EV_AVERAGE",
        "lastFoundAt": "2024-10-14T16:43:00.900Z",
        "type": "MONEYLINE_3WAY",
        "market_name": "Lazio @ Juventus",
        "participants": [
            "Juventus",
            "Lazio"
        ],
        "outcome_payout": 4.3,
        "source": "BET_RIVERS",
        "participant": "Lazio",
        "sport": "SOCCER",
        "implied_probability": 23.284102,
        "profit_potential": 330.0,
        "EV": 0.1216386,
        "event_start_time": "2024-10-19T18:45:00.000Z",
        "competition_instance_name": "2024-25 Italian Serie A"
    },
    {
        "key": "viyP-ykoq-TTQJ",
        "edge": "PLUS_EV_AVERAGE",
        "lastFoundAt": "2024-10-14T16:43:00.900Z",
        "type": "MONEYLINE_3WAY",
        "market_name": "Atalanta @ Venezia",
        "participants": [
            "Atalanta",
            "Venezia"
        ],
        "outcome_payout": 4.35,
        "source": "BET_PARX",
        "participant": null,
        "sport": null,
        "implied_probability": 23.152726,
        "profit_potential": 335.0,
        "EV": 0.7143581,
        "event_start_time": "2024-10-20T13:00:00.000Z",
        "competition_instance_name": "2024-25 Italian Serie A"
    },
    {
        "key": "WFGn-ykoq-SRMY",
        "edge": "PLUS_EV_AVERAGE",
        "lastFoundAt": "2024-10-14T16:43:00.900Z",
        "type": "MONEYLINE_3WAY",
        "market_name": "Hellas Verona @ Atalanta",
        "participants": [
            "Hellas Verona",
            "Atalanta"
        ],
        "outcome_payout": 8.5,
        "source": "BET_PARX",
        "participant": "Hellas Verona",
        "sport": "SOCCER",
        "implied_probability": 12.776968,
        "profit_potential": 750.0,
        "EV": 8.604228,
        "event_start_time": "2024-10-26T18:45:00.000Z",
        "competition_instance_name": "2024-25 Italian Serie A"
    },
    {
        "key": "Q6Wv-ykoq-Rc5e",
        "edge": "PLUS_EV_AVERAGE",
        "lastFoundAt": "2024-10-14T16:43:00.900Z",
        "type": "MONEYLINE_3WAY",
        "market_name": "Southampton @ Manchester City",
        "participants": [
            "Southampton",
            "Manchester City"
        ],
        "outcome_payout": 26.0,
        "source": "BET_PARX",
        "participant": "Southampton",
        "sport": "SOCCER",
        "implied_probability": 4.374859,
        "profit_potential": 2500.0,
        "EV": 13.746334,
        "event_start_time": "2024-10-26T14:00:00.000Z",
        "competition_instance_name": "2024-25 English Premier League"
    },
    {
        "key": "TomY-ykoq-6aIv",
        "edge": "PLUS_EV_AVERAGE",
        "lastFoundAt": "2024-10-14T16:43:00.900Z",
        "type": "MONEYLINE_3WAY",
        "market_name": "Southampton @ Manchester City",
        "participants": [
            "Southampton",
            "Manchester City"
        ],
        "outcome_payout": 26.0,
        "source": "BET_RIVERS",
        "participant": "Southampton",
        "sport": "SOCCER",
        "implied_probability": 4.374859,
        "profit_potential": 2500.0,
        "EV": 13.746334,
        "event_start_time": "2024-10-26T14:00:00.000Z",
        "competition_instance_name": "2024-25 English Premier League"
    },
    {
        "key": "gJwk-ykoq-Da0t",
        "edge": "PLUS_EV_AVERAGE",
        "lastFoundAt": "2024-10-14T16:43:00.900Z",
        "type": "MONEYLINE_3WAY",
        "market_name": "AFC Bournemouth @ Aston Villa",
        "participants": [
            "Aston Villa",
            "AFC Bournemouth"
        ],
        "outcome_payout": 4.35,
        "source": "BET_PARX",
        "participant": "AFC Bournemouth",
        "sport": "SOCCER",
        "implied_probability": 23.15562,
        "profit_potential": 335.0,
        "EV": 0.726947,
        "event_start_time": "2024-10-26T14:00:00.000Z",
        "competition_instance_name": "2024-25 English Premier League"
    },
    {
        "key": "UNV8-ykoq-nIO3",
        "edge": "PLUS_EV_AVERAGE",
        "lastFoundAt": "2024-10-14T16:43:00.900Z",
        "type": "MONEYLINE_3WAY",
        "market_name": "AFC Bournemouth @ Aston Villa",
        "participants": [
            "Aston Villa",
            "AFC Bournemouth"
        ],
        "outcome_payout": 4.4,
        "source": "BET_RIVERS",
        "participant": "AFC Bournemouth",
        "sport": "SOCCER",
        "implied_probability": 23.15562,
        "profit_potential": 340.0,
        "EV": 1.884728,
        "event_start_time": "2024-10-26T14:00:00.000Z",
        "competition_instance_name": "2024-25 English Premier League"
    },
    {
        "key": "09KR-ykoq-v5TQ",
        "edge": "PLUS_EV_AVERAGE",
        "lastFoundAt": "2024-10-14T16:43:00.900Z",
        "type": "MONEYLINE_3WAY",
        "market_name": "Ipswich Town @ Brentford",
        "participants": [
            "Brentford",
            "Ipswich Town"
        ],
        "outcome_payout": 4.9,
        "source": "BET_RIVERS",
        "participant": "Ipswich Town",
        "sport": "SOCCER",
        "implied_probability": 20.75176,
        "profit_potential": 390.0,
        "EV": 1.683624,
        "event_start_time": "2024-10-26T14:00:00.000Z",
        "competition_instance_name": "2024-25 English Premier League"
    },
    {
        "key": "0o73-ykoq-gyq2",
        "edge": "PLUS_EV_AVERAGE",
        "lastFoundAt": "2024-10-14T16:43:00.900Z",
        "type": "MONEYLINE_3WAY",
        "market_name": "Manchester United @ West Ham United",
        "participants": [
            "West Ham United",
            "Manchester United"
        ],
        "outcome_payout": 2.55,
        "source": "BET_RIVERS",
        "participant": "Manchester United",
        "sport": "SOCCER",
        "implied_probability": 39.553216,
        "profit_potential": 155.0,
        "EV": 0.8607008,
        "event_start_time": "2024-10-27T14:00:00.000Z",
        "competition_instance_name": "2024-25 English Premier League"
    },
    {
        "key": "Zui9-ykoq-PuAU",
        "edge": "PLUS_EV_AVERAGE",
        "lastFoundAt": "2024-10-14T16:43:00.900Z",
        "type": "MONEYLINE",
        "market_name": "Anadolu Efes @ Maccabi Tel Aviv",
        "participants": [
            "Anadolu Efes",
            "Maccabi Tel Aviv"
        ],
        "outcome_payout": 2.75,
        "source": "BOVADA",
        "participant": "Maccabi Tel Aviv",
        "sport": "BASKETBALL",
        "implied_probability": 37.318146,
        "profit_potential": 175.0,
        "EV": 2.6249015,
        "event_start_time": "2024-10-15T18:05:00.000Z",
        "competition_instance_name": "2024-25 EuroLeague"
    },
    {
        "key": "xkYo-ykoq-D3DT",
        "edge": "PLUS_EV_AVERAGE",
        "lastFoundAt": "2024-10-14T16:43:00.900Z",
        "type": "MONEYLINE_3WAY",
        "market_name": "Strasbourg @ Paris St Germain",
        "participants": [
            "Strasbourg",
            "Paris St Germain"
        ],
        "outcome_payout": 9.5,
        "source": "BET_MGM",
        "participant": "Strasbourg",
        "sport": "SOCCER",
        "implied_probability": 11.089855,
        "profit_potential": 850.0,
        "EV": 5.3536225,
        "event_start_time": "2024-10-19T19:00:00.000Z",
        "competition_instance_name": "2024-25 French Ligue 1"
    },
    {
        "key": "6hi7-ykoq-K3hP",
        "edge": "PLUS_EV_AVERAGE",
        "lastFoundAt": "2024-10-14T16:43:00.900Z",
        "type": "MONEYLINE_3WAY",
        "market_name": "Angers @ Toulouse",
        "participants": [
            "Toulouse",
            "Angers"
        ],
        "outcome_payout": 6.75,
        "source": "BET_RIVERS",
        "participant": "Angers",
        "sport": "SOCCER",
        "implied_probability": 14.946457,
        "profit_potential": 575.0,
        "EV": 0.88858475,
        "event_start_time": "2024-10-20T15:00:00.000Z",
        "competition_instance_name": "2024-25 French Ligue 1"
    },
    {
        "key": "z9rb-ykoq-Popk",
        "edge": "PLUS_EV_AVERAGE",
        "lastFoundAt": "2024-10-14T16:43:00.900Z",
        "type": "MONEYLINE_3WAY",
        "market_name": "Rayo Vallecano @ RCD Mallorca",
        "participants": [
            "RCD Mallorca",
            "Rayo Vallecano"
        ],
        "outcome_payout": 4.4,
        "source": "BET_RIVERS",
        "participant": "Rayo Vallecano",
        "sport": "SOCCER",
        "implied_probability": 22.808091,
        "profit_potential": 340.0,
        "EV": 0.3556004,
        "event_start_time": "2024-10-20T12:00:00.000Z",
        "competition_instance_name": "2024-25 Spanish La Liga"
    },
    {
        "key": "Fiif-ykoq-aox8",
        "edge": "PLUS_EV_AVERAGE",
        "lastFoundAt": "2024-10-14T16:43:00.900Z",
        "type": "MONEYLINE_3WAY",
        "market_name": "Sevilla @ Barcelona",
        "participants": [
            "Barcelona",
            "Sevilla"
        ],
        "outcome_payout": 10.5,
        "source": "BET_PARX",
        "participant": "Sevilla",
        "sport": "SOCCER",
        "implied_probability": 10.404805,
        "profit_potential": 950.0,
        "EV": 9.2504525,
        "event_start_time": "2024-10-20T19:00:00.000Z",
        "competition_instance_name": "2024-25 Spanish La Liga"
    },
    {
        "key": "18zM-ykoq-ovyj",
        "edge": "PLUS_EV_AVERAGE",
        "lastFoundAt": "2024-10-14T16:43:00.900Z",
        "type": "MONEYLINE_3WAY",
        "market_name": "Sevilla @ Barcelona",
        "participants": [
            "Barcelona",
            "Sevilla"
        ],
        "outcome_payout": 10.5,
        "source": "BET_RIVERS",
        "participant": "Sevilla",
        "sport": "SOCCER",
        "implied_probability": 10.404805,
        "profit_potential": 950.0,
        "EV": 9.2504525,
        "event_start_time": "2024-10-20T19:00:00.000Z",
        "competition_instance_name": "2024-25 Spanish La Liga"
    },
    {
        "key": "rRRA-ykoq-m0ZX",
        "edge": "PLUS_EV_AVERAGE",
        "lastFoundAt": "2024-10-14T16:43:00.900Z",
        "type": "MONEYLINE_3WAY",
        "market_name": "Legan\u00e9s @ Atletico Madrid",
        "participants": [
            "Atletico Madrid",
            "Legan\u00e9s"
        ],
        "outcome_payout": 11.0,
        "source": "BOVADA",
        "participant": "Legan\u00e9s",
        "sport": "SOCCER",
        "implied_probability": 9.803796,
        "profit_potential": 1000.0,
        "EV": 7.841756,
        "event_start_time": "2024-10-20T14:15:00.000Z",
        "competition_instance_name": "2024-25 Spanish La Liga"
    },
    {
        "key": "lrZf-ykoq-QKUl",
        "edge": "PLUS_EV_AVERAGE",
        "lastFoundAt": "2024-10-14T16:43:00.900Z",
        "type": "MONEYLINE_3WAY",
        "market_name": "Legan\u00e9s @ Atletico Madrid",
        "participants": [
            "Atletico Madrid",
            "Legan\u00e9s"
        ],
        "outcome_payout": 10.5,
        "source": "BET_PARX",
        "participant": "Legan\u00e9s",
        "sport": "SOCCER",
        "implied_probability": 9.803796,
        "profit_potential": 950.0,
        "EV": 2.939858,
        "event_start_time": "2024-10-20T14:15:00.000Z",
        "competition_instance_name": "2024-25 Spanish La Liga"
    },
    {
        "key": "ztPF-ykoq-9O3V",
        "edge": "PLUS_EV_AVERAGE",
        "lastFoundAt": "2024-10-14T16:43:00.900Z",
        "type": "MONEYLINE_3WAY",
        "market_name": "Legan\u00e9s @ Atletico Madrid",
        "participants": [
            "Atletico Madrid",
            "Legan\u00e9s"
        ],
        "outcome_payout": 10.5,
        "source": "BET_RIVERS",
        "participant": "Legan\u00e9s",
        "sport": "SOCCER",
        "implied_probability": 9.803796,
        "profit_potential": 950.0,
        "EV": 2.939858,
        "event_start_time": "2024-10-20T14:15:00.000Z",
        "competition_instance_name": "2024-25 Spanish La Liga"
    },
    {
        "key": "RSxM-ykoq-eVfL",
        "edge": "PLUS_EV_AVERAGE",
        "lastFoundAt": "2024-10-14T16:43:00.900Z",
        "type": "MONEYLINE_3WAY",
        "market_name": "VfL Bochum @ Hoffenheim",
        "participants": [
            "Hoffenheim",
            "VfL Bochum"
        ],
        "outcome_payout": 4.7,
        "source": "BET_RIVERS",
        "participant": null,
        "sport": null,
        "implied_probability": 21.602184,
        "profit_potential": 370.0,
        "EV": 1.5302648,
        "event_start_time": "2024-10-19T13:30:00.000Z",
        "competition_instance_name": "2024-25 German Bundesliga"
    },
    {
        "key": "2P1t-ykoq-CA3z",
        "edge": "PLUS_EV_AVERAGE",
        "lastFoundAt": "2024-10-14T16:43:00.900Z",
        "type": "MONEYLINE_3WAY",
        "market_name": "FC Augsburg @ Freiburg",
        "participants": [
            "Freiburg",
            "FC Augsburg"
        ],
        "outcome_payout": 4.2,
        "source": "BET_RIVERS",
        "participant": null,
        "sport": null,
        "implied_probability": 23.892186,
        "profit_potential": 320.0,
        "EV": 0.3471812,
        "event_start_time": "2024-10-19T13:30:00.000Z",
        "competition_instance_name": "2024-25 German Bundesliga"
    },
    {
        "key": "XmmS-ykoq-UIPq",
        "edge": "PLUS_EV_AVERAGE",
        "lastFoundAt": "2024-10-14T16:43:00.900Z",
        "type": "MONEYLINE_3WAY",
        "market_name": "Eintracht Frankfurt @ Bayer Leverkusen",
        "participants": [
            "Bayer Leverkusen",
            "Eintracht Frankfurt"
        ],
        "outcome_payout": 7.0,
        "source": "BET_RIVERS",
        "participant": "Eintracht Frankfurt",
        "sport": "SOCCER",
        "implied_probability": 14.779781,
        "profit_potential": 600.0,
        "EV": 3.458467,
        "event_start_time": "2024-10-19T13:30:00.000Z",
        "competition_instance_name": "2024-25 German Bundesliga"
    },
    {
        "key": "KRPy-ykoq-PlTL",
        "edge": "PLUS_EV_AVERAGE",
        "lastFoundAt": "2024-10-14T16:43:00.900Z",
        "type": "MONEYLINE_3WAY",
        "market_name": "Portland Timbers @ Seattle Sounders FC",
        "participants": [
            "Portland Timbers",
            "Seattle Sounders FC"
        ],
        "outcome_payout": 4.7,
        "source": "BET_RIVERS",
        "participant": "Portland Timbers",
        "sport": "SOCCER",
        "implied_probability": 21.669535,
        "profit_potential": 370.0,
        "EV": 1.8468145,
        "event_start_time": "2024-10-20T01:00:00.000Z",
        "competition_instance_name": "2024 Major League Soccer"
    },
    {
        "key": "itB2-ykoq-6a72",
        "edge": "PLUS_EV_AVERAGE",
        "lastFoundAt": "2024-10-14T16:43:00.900Z",
        "type": "MONEYLINE",
        "market_name": "Fresno State @ Nevada",
        "participants": [
            "Nevada",
            "Fresno State"
        ],
        "outcome_payout": 2.25,
        "source": "BET_MGM",
        "participant": "Nevada",
        "sport": "AMERICAN_FOOTBALL",
        "implied_probability": 44.685904,
        "profit_potential": 125.0,
        "EV": 0.543284,
        "event_start_time": "2024-10-19T02:30:00.000Z",
        "competition_instance_name": "2024 NCAA Division I Football"
    },
    {
        "key": "XsiE-ykoq-Qvxd",
        "edge": "PLUS_EV_AVERAGE",
        "lastFoundAt": "2024-10-14T16:43:00.900Z",
        "type": "MONEYLINE",
        "market_name": "FIU @ UTEP",
        "participants": [
            "UTEP",
            "FIU"
        ],
        "outcome_payout": 2.9,
        "source": "BOVADA",
        "participant": "UTEP",
        "sport": "AMERICAN_FOOTBALL",
        "implied_probability": 34.785326,
        "profit_potential": 190.0,
        "EV": 0.8774454,
        "event_start_time": "2024-10-17T01:00:00.000Z",
        "competition_instance_name": "2024 NCAA Division I Football"
    },
    {
        "key": "kk1e-ykoq-V0rP",
        "edge": "PLUS_EV_AVERAGE",
        "lastFoundAt": "2024-10-14T16:43:00.900Z",
        "type": "MONEYLINE",
        "market_name": "Florida State @ Duke",
        "participants": [
            "Duke",
            "Florida State"
        ],
        "outcome_payout": 2.55,
        "source": "ESPN_BET",
        "participant": "Florida State",
        "sport": "AMERICAN_FOOTBALL",
        "implied_probability": 39.343386,
        "profit_potential": 155.0,
        "EV": 0.3256343,
        "event_start_time": "2024-10-18T23:00:00.000Z",
        "competition_instance_name": "2024 NCAA Division I Football"
    },
    {
        "key": "MOf3-ykoq-SpvG",
        "edge": "PLUS_EV_AVERAGE",
        "lastFoundAt": "2024-10-14T16:43:00.900Z",
        "type": "MONEYLINE",
        "market_name": "Florida State @ Duke",
        "participants": [
            "Duke",
            "Florida State"
        ],
        "outcome_payout": 2.6,
        "source": "BOVADA",
        "participant": "Florida State",
        "sport": "AMERICAN_FOOTBALL",
        "implied_probability": 39.343386,
        "profit_potential": 160.0,
        "EV": 2.2928036,
        "event_start_time": "2024-10-18T23:00:00.000Z",
        "competition_instance_name": "2024 NCAA Division I Football"
    },
    {
        "key": "v2je-ykoq-Spxu",
        "edge": "PLUS_EV_AVERAGE",
        "lastFoundAt": "2024-10-14T16:43:00.900Z",
        "type": "MONEYLINE",
        "market_name": "Nebraska @ Indiana",
        "participants": [
            "Indiana",
            "Nebraska"
        ],
        "outcome_payout": 3.25,
        "source": "ESPN_BET",
        "participant": "Nebraska",
        "sport": "AMERICAN_FOOTBALL",
        "implied_probability": 31.791089,
        "profit_potential": 225.0,
        "EV": 3.32103925,
        "event_start_time": "2024-10-19T16:00:00.000Z",
        "competition_instance_name": "2024 NCAA Division I Football"
    },
    {
        "key": "z0Wb-ykoq-kcvW",
        "edge": "PLUS_EV_AVERAGE",
        "lastFoundAt": "2024-10-14T16:43:00.900Z",
        "type": "MONEYLINE",
        "market_name": "Louisiana @ Coastal Carolina",
        "participants": [
            "Coastal Carolina",
            "Louisiana"
        ],
        "outcome_payout": 2.6,
        "source": "BET_MGM",
        "participant": "Coastal Carolina",
        "sport": "AMERICAN_FOOTBALL",
        "implied_probability": 38.837455,
        "profit_potential": 160.0,
        "EV": 0.977383,
        "event_start_time": "2024-10-19T16:00:00.000Z",
        "competition_instance_name": "2024 NCAA Division I Football"
    },
    {
        "key": "UcBo-ykoq-8ytZ",
        "edge": "PLUS_EV_AVERAGE",
        "lastFoundAt": "2024-10-14T16:43:00.900Z",
        "type": "MONEYLINE",
        "market_name": "Virginia @ Clemson",
        "participants": [
            "Clemson",
            "Virginia"
        ],
        "outcome_payout": 10.8,
        "source": "FAN_DUEL",
        "participant": "Virginia",
        "sport": "AMERICAN_FOOTBALL",
        "implied_probability": 9.546404,
        "profit_potential": 980.0,
        "EV": 3.1011632,
        "event_start_time": "2024-10-19T16:00:00.000Z",
        "competition_instance_name": "2024 NCAA Division I Football"
    },
    {
        "key": "K8GZ-ykoq-DLMm",
        "edge": "PLUS_EV_AVERAGE",
        "lastFoundAt": "2024-10-14T16:43:00.900Z",
        "type": "MONEYLINE",
        "market_name": "Virginia @ Clemson",
        "participants": [
            "Clemson",
            "Virginia"
        ],
        "outcome_payout": 11.0,
        "source": "BET_MGM",
        "participant": "Virginia",
        "sport": "AMERICAN_FOOTBALL",
        "implied_probability": 9.546404,
        "profit_potential": 1000.0,
        "EV": 5.010444,
        "event_start_time": "2024-10-19T16:00:00.000Z",
        "competition_instance_name": "2024 NCAA Division I Football"
    },
    {
        "key": "yPxq-ykoq-2EM3",
        "edge": "PLUS_EV_AVERAGE",
        "lastFoundAt": "2024-10-14T16:43:00.900Z",
        "type": "MONEYLINE",
        "market_name": "Miami (FL) @ Louisville",
        "participants": [
            "Louisville",
            "Miami (FL)"
        ],
        "outcome_payout": 2.6,
        "source": "BOVADA",
        "participant": "Louisville",
        "sport": "AMERICAN_FOOTBALL",
        "implied_probability": 39.005581,
        "profit_potential": 160.0,
        "EV": 1.4145106,
        "event_start_time": "2024-10-19T17:00:00.000Z",
        "competition_instance_name": "2024 NCAA Division I Football"
    },
    {
        "key": "Sxdr-ykoq-TCS8",
        "edge": "PLUS_EV_AVERAGE",
        "lastFoundAt": "2024-10-14T16:43:00.900Z",
        "type": "MONEYLINE",
        "market_name": "Louisiana Tech @ New Mexico State",
        "participants": [
            "Louisiana Tech",
            "New Mexico State"
        ],
        "outcome_payout": 4.6,
        "source": "ESPN_BET",
        "participant": "New Mexico State",
        "sport": "AMERICAN_FOOTBALL",
        "implied_probability": 22.740429,
        "profit_potential": 360.0,
        "EV": 4.6059734,
        "event_start_time": "2024-10-16T01:00:00.000Z",
        "competition_instance_name": "2024 NCAA Division I Football"
    },
    {
        "key": "yJKL-ykoq-oNFA",
        "edge": "PLUS_EV_AVERAGE",
        "lastFoundAt": "2024-10-14T16:43:00.900Z",
        "type": "MONEYLINE",
        "market_name": "Louisiana Tech @ New Mexico State",
        "participants": [
            "Louisiana Tech",
            "New Mexico State"
        ],
        "outcome_payout": 4.4,
        "source": "DRAFT_KINGS",
        "participant": "New Mexico State",
        "sport": "AMERICAN_FOOTBALL",
        "implied_probability": 22.740429,
        "profit_potential": 340.0,
        "EV": 0.0578876,
        "event_start_time": "2024-10-16T01:00:00.000Z",
        "competition_instance_name": "2024 NCAA Division I Football"
    },
    {
        "key": "ikRD-ykoq-1JzV",
        "edge": "PLUS_EV_AVERAGE",
        "lastFoundAt": "2024-10-14T16:43:00.900Z",
        "type": "MONEYLINE_3WAY",
        "market_name": "Southampton @ Manchester City",
        "participants": [
            "Southampton",
            "Manchester City"
        ],
        "outcome_payout": 11.0,
        "source": "DRAFT_KINGS",
        "participant": null,
        "sport": null,
        "implied_probability": 9.269331,
        "profit_potential": 1000.0,
        "EV": 1.962641,
        "event_start_time": "2024-10-26T14:00:00.000Z",
        "competition_instance_name": "2024-25 English Premier League"
    },
    {
        "key": "Id4B-ykoq-GZjX",
        "edge": "PLUS_EV_AVERAGE",
        "lastFoundAt": "2024-10-14T16:43:00.900Z",
        "type": "MONEYLINE_3WAY",
        "market_name": "Southampton @ Manchester City",
        "participants": [
            "Southampton",
            "Manchester City"
        ],
        "outcome_payout": 24.0,
        "source": "FAN_DUEL",
        "participant": "Southampton",
        "sport": "SOCCER",
        "implied_probability": 4.374859,
        "profit_potential": 2300.0,
        "EV": 4.996616,
        "event_start_time": "2024-10-26T14:00:00.000Z",
        "competition_instance_name": "2024-25 English Premier League"
    },
    {
        "key": "2kpE-ykoq-QQtc",
        "edge": "PLUS_EV_AVERAGE",
        "lastFoundAt": "2024-10-14T16:43:00.900Z",
        "type": "MONEYLINE",
        "market_name": "Houston @ Kansas",
        "participants": [
            "Houston",
            "Kansas"
        ],
        "outcome_payout": 3.2,
        "source": "ESPN_BET",
        "participant": "Houston",
        "sport": "AMERICAN_FOOTBALL",
        "implied_probability": 31.363884,
        "profit_potential": 220.0,
        "EV": 0.3644288,
        "event_start_time": "2024-10-19T20:00:00.000Z",
        "competition_instance_name": "2024 NCAA Division I Football"
    },
    {
        "key": "y1Ni-ykoq-5oP4",
        "edge": "PLUS_EV_AVERAGE",
        "lastFoundAt": "2024-10-14T16:43:00.900Z",
        "type": "MONEYLINE_3WAY",
        "market_name": "West Ham United @ Tottenham Hotspur",
        "participants": [
            "Tottenham Hotspur",
            "West Ham United"
        ],
        "outcome_payout": 5.0,
        "source": "BOVADA",
        "participant": null,
        "sport": null,
        "implied_probability": 20.308726,
        "profit_potential": 400.0,
        "EV": 1.54363,
        "event_start_time": "2024-10-19T11:30:00.000Z",
        "competition_instance_name": "2024-25 English Premier League"
    },
    {
        "key": "30Cs-ykoq-va9L",
        "edge": "PLUS_EV_AVERAGE",
        "lastFoundAt": "2024-10-14T16:43:00.900Z",
        "type": "MONEYLINE_3WAY",
        "market_name": "West Ham United @ Tottenham Hotspur",
        "participants": [
            "Tottenham Hotspur",
            "West Ham United"
        ],
        "outcome_payout": 6.1,
        "source": "BET_PARX",
        "participant": "West Ham United",
        "sport": "SOCCER",
        "implied_probability": 16.658069,
        "profit_potential": 510.0,
        "EV": 1.6142209,
        "event_start_time": "2024-10-19T11:30:00.000Z",
        "competition_instance_name": "2024-25 English Premier League"
    },
    {
        "key": "uW6l-ykoq-v8XM",
        "edge": "PLUS_EV_AVERAGE",
        "lastFoundAt": "2024-10-14T16:43:00.900Z",
        "type": "MONEYLINE_3WAY",
        "market_name": "West Ham United @ Tottenham Hotspur",
        "participants": [
            "Tottenham Hotspur",
            "West Ham United"
        ],
        "outcome_payout": 6.25,
        "source": "BET_RIVERS",
        "participant": "West Ham United",
        "sport": "SOCCER",
        "implied_probability": 16.658069,
        "profit_potential": 525.0,
        "EV": 4.11293125,
        "event_start_time": "2024-10-19T11:30:00.000Z",
        "competition_instance_name": "2024-25 English Premier League"
    },
    {
        "key": "e1VV-ykoq-24FM",
        "edge": "PLUS_EV_AVERAGE",
        "lastFoundAt": "2024-10-14T16:43:00.900Z",
        "type": "MONEYLINE_3WAY",
        "market_name": "Manchester City @ Wolverhampton Wanderers",
        "participants": [
            "Manchester City",
            "Wolverhampton Wanderers"
        ],
        "outcome_payout": 10.0,
        "source": "FAN_DUEL",
        "participant": "Wolverhampton Wanderers",
        "sport": "SOCCER",
        "implied_probability": 10.894968,
        "profit_potential": 900.0,
        "EV": 8.94968,
        "event_start_time": "2024-10-20T13:00:00.000Z",
        "competition_instance_name": "2024-25 English Premier League"
    },
    {
        "key": "7iWw-ykoq-dJMO",
        "edge": "PLUS_EV_AVERAGE",
        "lastFoundAt": "2024-10-14T16:43:00.900Z",
        "type": "MONEYLINE_3WAY",
        "market_name": "Brentford @ Manchester United",
        "participants": [
            "Brentford",
            "Manchester United"
        ],
        "outcome_payout": 5.1,
        "source": "BET_RIVERS",
        "participant": "Brentford",
        "sport": "SOCCER",
        "implied_probability": 19.918537,
        "profit_potential": 410.0,
        "EV": 1.5845387,
        "event_start_time": "2024-10-19T14:00:00.000Z",
        "competition_instance_name": "2024-25 English Premier League"
    },
    {
        "key": "Cif3-ykoq-m5uA",
        "edge": "PLUS_EV_AVERAGE",
        "lastFoundAt": "2024-10-14T16:43:00.900Z",
        "type": "MONEYLINE",
        "market_name": "East Carolina @ Army",
        "participants": [
            "Army",
            "East Carolina"
        ],
        "outcome_payout": 6.7,
        "source": "FAN_DUEL",
        "participant": "East Carolina",
        "sport": "AMERICAN_FOOTBALL",
        "implied_probability": 15.178768,
        "profit_potential": 570.0,
        "EV": 1.6977456,
        "event_start_time": "2024-10-19T16:00:00.000Z",
        "competition_instance_name": "2024 NCAA Division I Football"
    },
    {
        "key": "hrfp-ykoq-vHcG",
        "edge": "PLUS_EV_AVERAGE",
        "lastFoundAt": "2024-10-14T16:43:00.900Z",
        "type": "MONEYLINE",
        "market_name": "UAB @ South Florida",
        "participants": [
            "South Florida",
            "UAB"
        ],
        "outcome_payout": 5.0,
        "source": "FAN_DUEL",
        "participant": "UAB",
        "sport": "AMERICAN_FOOTBALL",
        "implied_probability": 20.089624,
        "profit_potential": 400.0,
        "EV": 0.44812,
        "event_start_time": "2024-10-19T19:30:00.000Z",
        "competition_instance_name": "2024 NCAA Division I Football"
    },
    {
        "key": "ykFb-ykoq-zMXf",
        "edge": "PLUS_EV_AVERAGE",
        "lastFoundAt": "2024-10-14T16:43:00.900Z",
        "type": "MONEYLINE",
        "market_name": "UAB @ South Florida",
        "participants": [
            "South Florida",
            "UAB"
        ],
        "outcome_payout": 5.0,
        "source": "ESPN_BET",
        "participant": "UAB",
        "sport": "AMERICAN_FOOTBALL",
        "implied_probability": 20.089624,
        "profit_potential": 400.0,
        "EV": 0.44812,
        "event_start_time": "2024-10-19T19:30:00.000Z",
        "competition_instance_name": "2024 NCAA Division I Football"
    },
    {
        "key": "JGe6-ykoq-rxVT",
        "edge": "PLUS_EV_AVERAGE",
        "lastFoundAt": "2024-10-14T16:43:00.900Z",
        "type": "MONEYLINE",
        "market_name": "UAB @ South Florida",
        "participants": [
            "South Florida",
            "UAB"
        ],
        "outcome_payout": 5.1,
        "source": "BOVADA",
        "participant": "UAB",
        "sport": "AMERICAN_FOOTBALL",
        "implied_probability": 20.089624,
        "profit_potential": 410.0,
        "EV": 2.4570824,
        "event_start_time": "2024-10-19T19:30:00.000Z",
        "competition_instance_name": "2024 NCAA Division I Football"
    },
    {
        "key": "ijyR-ykoq-HISA",
        "edge": "PLUS_EV_AVERAGE",
        "lastFoundAt": "2024-10-14T16:43:00.900Z",
        "type": "MONEYLINE",
        "market_name": "Ball State @ Vanderbilt",
        "participants": [
            "Vanderbilt",
            "Ball State"
        ],
        "outcome_payout": 17.0,
        "source": "FAN_DUEL",
        "participant": "Ball State",
        "sport": "AMERICAN_FOOTBALL",
        "implied_probability": 6.571949,
        "profit_potential": 1600.0,
        "EV": 11.723133,
        "event_start_time": "2024-10-19T23:00:00.000Z",
        "competition_instance_name": "2024 NCAA Division I Football"
    },
    {
        "key": "59l1-ykoq-0c0B",
        "edge": "PLUS_EV_AVERAGE",
        "lastFoundAt": "2024-10-14T16:43:00.900Z",
        "type": "MONEYLINE",
        "market_name": "Ball State @ Vanderbilt",
        "participants": [
            "Vanderbilt",
            "Ball State"
        ],
        "outcome_payout": 17.0,
        "source": "BET_PARX",
        "participant": "Ball State",
        "sport": "AMERICAN_FOOTBALL",
        "implied_probability": 6.571949,
        "profit_potential": 1600.0,
        "EV": 11.723133,
        "event_start_time": "2024-10-19T23:00:00.000Z",
        "competition_instance_name": "2024 NCAA Division I Football"
    },
    {
        "key": "Gr0A-ykoq-SshE",
        "edge": "PLUS_EV_AVERAGE",
        "lastFoundAt": "2024-10-14T16:43:00.900Z",
        "type": "MONEYLINE",
        "market_name": "Texas A&M @ Mississippi State",
        "participants": [
            "Mississippi State",
            "Texas A&M"
        ],
        "outcome_payout": 6.0,
        "source": "ESPN_BET",
        "participant": "Mississippi State",
        "sport": "AMERICAN_FOOTBALL",
        "implied_probability": 16.875273,
        "profit_potential": 500.0,
        "EV": 1.251638,
        "event_start_time": "2024-10-19T20:15:00.000Z",
        "competition_instance_name": "2024 NCAA Division I Football"
    },
    {
        "key": "H8Xf-ykoq-zYsu",
        "edge": "PLUS_EV_AVERAGE",
        "lastFoundAt": "2024-10-14T16:43:00.900Z",
        "type": "MONEYLINE",
        "market_name": "Arkansas State @ Southern Miss",
        "participants": [
            "Arkansas State",
            "Southern Miss"
        ],
        "outcome_payout": 3.1,
        "source": "ESPN_BET",
        "participant": "Southern Miss",
        "sport": "AMERICAN_FOOTBALL",
        "implied_probability": 32.411767,
        "profit_potential": 210.0,
        "EV": 0.4764777,
        "event_start_time": "2024-10-19T23:00:00.000Z",
        "competition_instance_name": "2024 NCAA Division I Football"
    },
    {
        "key": "cA4p-ykoq-kLIO",
        "edge": "PLUS_EV_AVERAGE",
        "lastFoundAt": "2024-10-14T16:43:00.900Z",
        "type": "MONEYLINE",
        "market_name": "Charlotte @ Navy",
        "participants": [
            "Charlotte",
            "Navy"
        ],
        "outcome_payout": 7.25,
        "source": "BET_MGM",
        "participant": "Charlotte",
        "sport": "AMERICAN_FOOTBALL",
        "implied_probability": 14.146813,
        "profit_potential": 625.0,
        "EV": 2.56439425,
        "event_start_time": "2024-10-19T19:30:00.000Z",
        "competition_instance_name": "2024 NCAA Division I Football"
    },
    {
        "key": "b0nc-ykoq-L9xv",
        "edge": "PLUS_EV_AVERAGE",
        "lastFoundAt": "2024-10-14T16:43:00.900Z",
        "type": "MONEYLINE",
        "market_name": "Texas State @ Old Dominion",
        "participants": [
            "Old Dominion",
            "Texas State"
        ],
        "outcome_payout": 4.1,
        "source": "BOVADA",
        "participant": "Old Dominion",
        "sport": "AMERICAN_FOOTBALL",
        "implied_probability": 24.88947,
        "profit_potential": 310.0,
        "EV": 2.046827,
        "event_start_time": "2024-10-19T19:30:00.000Z",
        "competition_instance_name": "2024 NCAA Division I Football"
    },
    {
        "key": "fgtV-ykoq-J1Vr",
        "edge": "PLUS_EV_AVERAGE",
        "lastFoundAt": "2024-10-14T16:43:00.900Z",
        "type": "MONEYLINE",
        "market_name": "Hawaii @ Washington State",
        "participants": [
            "Hawaii",
            "Washington State"
        ],
        "outcome_payout": 8.6,
        "source": "FAN_DUEL",
        "participant": "Hawaii",
        "sport": "AMERICAN_FOOTBALL",
        "implied_probability": 11.660067,
        "profit_potential": 760.0,
        "EV": 0.2765762,
        "event_start_time": "2024-10-19T19:30:00.000Z",
        "competition_instance_name": "2024 NCAA Division I Football"
    },
    {
        "key": "hCD7-ykoq-wq4A",
        "edge": "PLUS_EV_AVERAGE",
        "lastFoundAt": "2024-10-14T16:43:00.900Z",
        "type": "MONEYLINE",
        "market_name": "Kent State @ Bowling Green",
        "participants": [
            "Kent State",
            "Bowling Green"
        ],
        "outcome_payout": 11.0,
        "source": "ESPN_BET",
        "participant": "Kent State",
        "sport": "AMERICAN_FOOTBALL",
        "implied_probability": 10.049107,
        "profit_potential": 1000.0,
        "EV": 10.540177,
        "event_start_time": "2024-10-19T19:30:00.000Z",
        "competition_instance_name": "2024 NCAA Division I Football"
    },
    {
        "key": "nPcs-ykoq-Y9H0",
        "edge": "PLUS_EV_AVERAGE",
        "lastFoundAt": "2024-10-14T16:43:00.900Z",
        "type": "MONEYLINE",
        "market_name": "Kent State @ Bowling Green",
        "participants": [
            "Kent State",
            "Bowling Green"
        ],
        "outcome_payout": 11.0,
        "source": "BET_MGM",
        "participant": "Kent State",
        "sport": "AMERICAN_FOOTBALL",
        "implied_probability": 10.049107,
        "profit_potential": 1000.0,
        "EV": 10.540177,
        "event_start_time": "2024-10-19T19:30:00.000Z",
        "competition_instance_name": "2024 NCAA Division I Football"
    },
    {
        "key": "ssdf-ykoq-DFzY",
        "edge": "PLUS_EV_AVERAGE",
        "lastFoundAt": "2024-10-14T16:43:00.900Z",
        "type": "MONEYLINE",
        "market_name": "UNLV @ Oregon State",
        "participants": [
            "UNLV",
            "Oregon State"
        ],
        "outcome_payout": 3.4,
        "source": "BOVADA",
        "participant": "Oregon State",
        "sport": "AMERICAN_FOOTBALL",
        "implied_probability": 29.787626,
        "profit_potential": 240.0,
        "EV": 1.2779284,
        "event_start_time": "2024-10-20T02:00:00.000Z",
        "competition_instance_name": "2024 NCAA Division I Football"
    },
    {
        "key": "Uh08-ykoq-YIM0",
        "edge": "PLUS_EV_AVERAGE",
        "lastFoundAt": "2024-10-14T16:43:00.900Z",
        "type": "MONEYLINE",
        "market_name": "SMU @ Stanford",
        "participants": [
            "SMU",
            "Stanford"
        ],
        "outcome_payout": 6.0,
        "source": "ESPN_BET",
        "participant": "Stanford",
        "sport": "AMERICAN_FOOTBALL",
        "implied_probability": 16.797487,
        "profit_potential": 500.0,
        "EV": 0.784922,
        "event_start_time": "2024-10-20T00:00:00.000Z",
        "competition_instance_name": "2024 NCAA Division I Football"
    },
    {
        "key": "ojfL-ykoq-uNW7",
        "edge": "PLUS_EV_AVERAGE",
        "lastFoundAt": "2024-10-14T16:43:00.900Z",
        "type": "MONEYLINE",
        "market_name": "Iowa @ Michigan State",
        "participants": [
            "Iowa",
            "Michigan State"
        ],
        "outcome_payout": 3.0,
        "source": "BOVADA",
        "participant": "Michigan State",
        "sport": "AMERICAN_FOOTBALL",
        "implied_probability": 33.412254,
        "profit_potential": 200.0,
        "EV": 0.236762,
        "event_start_time": "2024-10-19T23:30:00.000Z",
        "competition_instance_name": "2024 NCAA Division I Football"
    },
    {
        "key": "Coyi-ykoq-QhqV",
        "edge": "PLUS_EV_AVERAGE",
        "lastFoundAt": "2024-10-14T16:43:00.900Z",
        "type": "MONEYLINE",
        "market_name": "Alabama @ Tennessee",
        "participants": [
            "Alabama",
            "Tennessee"
        ],
        "outcome_payout": 2.25,
        "source": "BOVADA",
        "participant": "Tennessee",
        "sport": "AMERICAN_FOOTBALL",
        "implied_probability": 44.815528,
        "profit_potential": 125.0,
        "EV": 0.834938,
        "event_start_time": "2024-10-19T19:30:00.000Z",
        "competition_instance_name": "2024 NCAA Division I Football"
    },
    {
        "key": "0hDY-ykoq-K6pO",
        "edge": "PLUS_EV_AVERAGE",
        "lastFoundAt": "2024-10-14T16:43:00.900Z",
        "type": "MONEYLINE_3WAY",
        "market_name": "Watford @ Luton Town",
        "participants": [
            "Luton Town",
            "Watford"
        ],
        "outcome_payout": 3.75,
        "source": "BET_RIVERS",
        "participant": null,
        "sport": null,
        "implied_probability": 26.70699,
        "profit_potential": 275.0,
        "EV": 0.1512125,
        "event_start_time": "2024-10-19T11:30:00.000Z",
        "competition_instance_name": "2024-25 English Football League Championship"
    },
    {
        "key": "MaCe-ykoq-AtSg",
        "edge": "PLUS_EV_AVERAGE",
        "lastFoundAt": "2024-10-14T16:43:00.900Z",
        "type": "MONEYLINE_3WAY",
        "market_name": "Bristol City @ Middlesbrough",
        "participants": [
            "Middlesbrough",
            "Bristol City"
        ],
        "outcome_payout": 4.1,
        "source": "BET_RIVERS",
        "participant": null,
        "sport": null,
        "implied_probability": 24.575316,
        "profit_potential": 310.0,
        "EV": 0.7587956,
        "event_start_time": "2024-10-19T14:00:00.000Z",
        "competition_instance_name": "2024-25 English Football League Championship"
    },
    {
        "key": "2gvg-ykoq-bacj",
        "edge": "PLUS_EV_AVERAGE",
        "lastFoundAt": "2024-10-14T16:43:00.900Z",
        "type": "MONEYLINE",
        "market_name": "Carolina Panthers @ Washington Commanders",
        "participants": [
            "Carolina Panthers",
            "Washington Commanders"
        ],
        "outcome_payout": 4.2,
        "source": "FAN_DUEL",
        "participant": "Carolina Panthers",
        "sport": "AMERICAN_FOOTBALL",
        "implied_probability": 23.855679,
        "profit_potential": 320.0,
        "EV": 0.1938518,
        "event_start_time": "2024-10-20T20:05:00.000Z",
        "competition_instance_name": "2024-25 National Football League"
    },
    {
        "key": "6wfc-ykoq-MJZm",
        "edge": "PLUS_EV_AVERAGE",
        "lastFoundAt": "2024-10-14T16:43:00.900Z",
        "type": "MONEYLINE_3WAY",
        "market_name": "Juventus @ Inter Milan",
        "participants": [
            "Juventus",
            "Inter Milan"
        ],
        "outcome_payout": 4.1,
        "source": "BET_RIVERS",
        "participant": null,
        "sport": null,
        "implied_probability": 25.160179,
        "profit_potential": 310.0,
        "EV": 3.1567339,
        "event_start_time": "2024-10-27T17:00:00.000Z",
        "competition_instance_name": "2024-25 Italian Serie A"
    },
    {
        "key": "DhRc-ykoq-ZWVi",
        "edge": "PLUS_EV_AVERAGE",
        "lastFoundAt": "2024-10-14T16:43:00.900Z",
        "type": "MONEYLINE_3WAY",
        "market_name": "Lecce @ Napoli",
        "participants": [
            "Lecce",
            "Napoli"
        ],
        "outcome_payout": 5.5,
        "source": "BET_RIVERS",
        "participant": null,
        "sport": null,
        "implied_probability": 18.291739,
        "profit_potential": 450.0,
        "EV": 0.6045645,
        "event_start_time": "2024-10-26T13:00:00.000Z",
        "competition_instance_name": "2024-25 Italian Serie A"
    },
    {
        "key": "GBr2-ykoq-T3mS",
        "edge": "PLUS_EV_AVERAGE",
        "lastFoundAt": "2024-10-14T16:43:00.900Z",
        "type": "MONEYLINE",
        "market_name": "Los Angeles Chargers @ Arizona Cardinals",
        "participants": [
            "Arizona Cardinals",
            "Los Angeles Chargers"
        ],
        "outcome_payout": 2.3,
        "source": "BOVADA",
        "participant": "Arizona Cardinals",
        "sport": "AMERICAN_FOOTBALL",
        "implied_probability": 43.559793,
        "profit_potential": 130.0,
        "EV": 0.1875239,
        "event_start_time": "2024-10-22T01:00:00.000Z",
        "competition_instance_name": "2024-25 National Football League"
    },
    {
        "key": "jnZP-ykoq-eziG",
        "edge": "PLUS_EV_AVERAGE",
        "lastFoundAt": "2024-10-14T16:43:00.900Z",
        "type": "MONEYLINE_3WAY",
        "market_name": "Juventus @ Inter Milan",
        "participants": [
            "Juventus",
            "Inter Milan"
        ],
        "outcome_payout": 4.0,
        "source": "BET_PARX",
        "participant": null,
        "sport": null,
        "implied_probability": 25.160179,
        "profit_potential": 300.0,
        "EV": 0.640716,
        "event_start_time": "2024-10-27T17:00:00.000Z",
        "competition_instance_name": "2024-25 Italian Serie A"
    }
]